azure_speech_tools/__init__.py
azure_speech_tools/tools/__init__.py
azure_speech_tools/tools/azure_speech_sr.py
azure_speech_tools/tools/azure_speech_tts.py
azure_speech_tools/tools/utils.py
azure_speech_tools/yamls/azure_speech_sr.yaml
azure_speech_tools/yamls/azure_speech_tts.yaml
azure_speech_tools-0.0.5.dist-info/METADATA
azure_speech_tools-0.0.5.dist-info/WHEEL
azure_speech_tools-0.0.5.dist-info/entry_points.txt
azure_speech_tools-0.0.5.dist-info/top_level.txt
azure_speech_tools-0.0.5.dist-info/RECORD
